log_factory/__init__.py
log_factory-0.1.1.dist-info/DESCRIPTION.rst
log_factory-0.1.1.dist-info/LICENSE.txt
log_factory-0.1.1.dist-info/METADATA
log_factory-0.1.1.dist-info/RECORD
log_factory-0.1.1.dist-info/WHEEL
log_factory-0.1.1.dist-info/metadata.json
log_factory-0.1.1.dist-info/top_level.txt
