Metadata-Version: 2.0
Name: log-factory
Version: 0.1.1
Summary: UNKNOWN
Home-page: https://github.com/colinp85/log_factory
Author: cp
License: MIT
Platform: UNKNOWN
Requires-Python: >=2.6
